{
    "label": "actualArrivalRelatedDateTime",
    "uri": "unece:actualArrivalRelatedDateTime",
    "comment": "The date, time, date time or other date time value of the actual arrival related to this transport event.",
    "businessDomain": "transport",
    "rangeIncludes": [
        {
            "uri": "xsd:string"
        }
    ],
    "domainIncludes": [
        {
            "uri": "unece:TransportEvent",
            "comment": "A significant occurrence or happening during transport.,A referenced significant occurrence or happening during transport."
        }
    ]
}