{
    "label": "applicableTax",
    "uri": "unece:applicableTax",
    "comment": "A tax applicable to this header trade settlement.",
    "businessDomain": "finance",
    "rangeIncludes": [
        {
            "uri": "unece:Tax"
        }
    ],
    "domainIncludes": [
        {
            "uri": "unece:PaymentTradeSettlement",
            "comment": "The information that enables the reconciliation of a payment with the item(s) that the payment is intended to settle, for example a commercial invoice."
        }
    ]
}