{
    "label": "applicableGoodsCharacteristic",
    "uri": "unece:applicableGoodsCharacteristic",
    "comment": "A distinguishing material feature applicable to this trade product instance.",
    "businessDomain": "transport",
    "rangeIncludes": [
        {
            "uri": "unece:GoodsCharacteristic"
        }
    ],
    "domainIncludes": [
        {
            "uri": "unece:SupplyChainPackaging",
            "comment": "Any material with which supply chain goods are packaged, such as a box or bubble wrap."
        }
    ]
}