{
    "label": "applicableProcessCharacteristic",
    "uri": "unece:applicableProcessCharacteristic",
    "comment": "A process characteristic applicable to this process certificate.",
    "businessDomain": "agriculture",
    "rangeIncludes": [
        {
            "uri": "unece:ProcessCharacteristic"
        }
    ],
    "domainIncludes": [
        {
            "uri": "unece:ProcessCertificate",
            "comment": "A piece of written, printed or electronic matter that provides information or evidence that a process has met required criteria."
        }
    ]
}