{
    "label": "Area",
    "uri": "unece:Area",
    "comment": "A named, delimited and identified part of a land and or water surface of the globe subject to dedicated uniform agricultural treatment.",
    "objectProperties": [
        {
            "uri": "unece:applicableAgriculturalCharacteristic",
            "type": "unece:AgriculturalCharacteristic",
            "comment": "An agricultural characteristic applicable to this agricultural zone area."
        },
        {
            "uri": "unece:appliedAgriculturalApplication",
            "type": "unece:AgriculturalApplication",
            "comment": "A specified agricultural application applied to this agricultural zone area."
        },
        {
            "uri": "unece:designatedSection",
            "type": "xsd:string",
            "comment": "The designated section, expressed as text, of this agricultural zone area."
        },
        {
            "uri": "unece:harvestedProduce",
            "type": "unece:Produce",
            "comment": "Crop produce harvested from this agricultural zone area."
        },
        {
            "uri": "unece:identifier",
            "type": "xsd:string",
            "comment": "The identifier for this agricultural zone area."
        },
        {
            "uri": "unece:multiSurfaceTypeCode",
            "type": "xsd:string",
            "comment": "The code specifying the multi-surface type for this agricultural zone area."
        },
        {
            "uri": "unece:name",
            "type": "xsd:string",
            "comment": "The name, expressed as text, for this agricultural zone area."
        },
        {
            "uri": "unece:specifiedLocation",
            "type": "unece:Location",
            "comment": "The referenced location specified for this agricultural zone area."
        },
        {
            "uri": "unece:specifiedPlot",
            "type": "unece:Plot",
            "comment": "A crop plot specified for this agricultural zone area."
        },
        {
            "uri": "unece:subordinateArea",
            "type": "unece:Area",
            "comment": "An agricultural zone area subordinate to this agricultural zone area."
        },
        {
            "uri": "unece:thirdPartyIssuedId",
            "type": "xsd:string",
            "comment": "An identifier issued by a third party for this agricultural zone area."
        }
    ],
    "referencedBy": [
        {
            "uri": "unece:appliedArea",
            "comment": "A specified agricultural application applied to this agricultural zone area."
        },
        {
            "uri": "unece:specifiedArea",
            "comment": "An agricultural zone area specified for this crop plot."
        },
        {
            "uri": "unece:subordinateArea",
            "comment": "An agricultural zone area subordinate to this agricultural zone area."
        }
    ]
}