{
    "label": "associatedFinancingRequestResultDocument",
    "uri": "unece:associatedFinancingRequestResultDocument",
    "comment": "The financing request result document associated with this supply chain trade transaction.",
    "businessDomain": "trade",
    "rangeIncludes": [
        {
            "uri": "unece:FinancingRequestResultDocument"
        }
    ],
    "domainIncludes": [
        {
            "uri": "unece:SupplyChainTradeTransaction",
            "comment": "A group of supply chain trade line items, trade agreement, trade delivery and trade settlement details."
        }
    ]
}