{
    "label": "consigneeReceiptLocation",
    "uri": "unece:consigneeReceiptLocation",
    "comment": "The location at which this supply chain consignment will be or has been received by the consignee.",
    "rangeIncludes": [
        {
            "uri": "unece:LogisticsLocation",
            "comment": "A logistics related physical location or place."
        }
    ],
    "domainIncludes": [
        {
            "uri": "unece:Consignment",
            "comment": "A separately identifiable collection of ..."
        }
    ]
}