
{
    "label": "personalLanguageProficiencyLanguageId",
    "uri": "core:LanguageProficiency.personalLanguageProficiencyLanguageId",
    "comment": "The identifier of the language for which this personal language proficiency is defined.",
    "domain": "core",
    "rangeIncludes": [
        {
            "uri": "core:LanguageId"
        }
    ],
    "domainIncludes": [
        {
            "uri": "core:LanguageProficiency",
            "comment": "Skills in any principal method of human communication, consisting of words used in a structured and conventional way and conveyed by speech, writing, or gesture."
        }
    ]
}