
{
    "label": "clearingSystemName",
    "uri": "unece:DebtorFinancialInstitution.clearingSystemName",
    "comment": "The clearing system name, expressed as text, for this creditor financial institution.",
    "rangeIncludes": [
        {
            "uri": "schema:Text"
        }
    ],
    "domainIncludes": [
        {
            "uri": "unece:DebtorFinancialInstitution",
            "comment": "A bank, building society, credit union, stock brokerage, or similar business of the party that owes money."
        }
    ]
}