{
    "label": "designatedSection",
    "uri": "unece:designatedSection",
    "comment": "The designated section, expressed as text, of this agricultural zone area.",
    "rangeIncludes": [
        {
            "uri": "xsd:string"
        }
    ],
    "domainIncludes": [
        {
            "uri": "unece:AgriculturalZoneArea",
            "comment": "A named, delimited and identified part of a land and or water surface of the globe subject to dedicated uniform agricultural treatment."
        }
    ]
}