
{
    "label": "exemptionClaimantParty",
    "uri": "unece:exemptionClaimantParty",
    "comment": "A party who claims an exemption from this cross-border regulatory procedure.",
    "rangeIncludes": [
        {
            "uri": "unece:TradeParty",
            "comment": "An individual, a group, or a body having a role in a trade business function."
        }
    ],
    "domainIncludes": [
        {
            "uri": "unece:RegulatoryProcedure",
            "comment": "A set of formal steps to satisfy a regulation, law or convention."
        }
    ]
}