
{
    "label": "explicit_policy_or_set_of_criteria_addressing_cultural_and_religion_rights",
    "uri": "sustainability:explicit_policy_or_set_of_criteria_addressing_cultural_and_religion_rights",
    "comment": "Does the standard system require an explicit policy or set of criteria addressing cultural and religion rights",
    "rangeIncludes": [
        {
            "uri": "xsd:boolean"
        }
    ],
    "domainIncludes": [
        {
            "uri": "sustainability:ComplianceToLegislation",
            "comment": ""
        }
    ]
}