
{
    "label": "appliedAgriculturalApplication",
    "uri": "unece:FieldCrop.appliedAgriculturalApplication",
    "comment": "A specified agricultural application applied to this agricultural zone area.",
    "rangeIncludes": [
        {
            "uri": "unece:AgriculturalApplication",
            "comment": "Any substance such as seed, fertilizer, water, gas or chemical applied to an agricultural field, substrate, construction, plant, animal or product."
        }
    ],
    "domainIncludes": [
        {
            "uri": "unece:FieldCrop",
            "comment": "A field with one or more cultivated plants or produce from one or more botanical species or varieties."
        }
    ]
}