
{
    "label": "multipleReasonIndicator",
    "uri": "finance:TradePrice.multipleReasonIndicator",
    "comment": "The indication of whether or not multiple reasons affect this trade price.",
    "domain": "finance",
    "rangeIncludes": [
        {
            "uri": "schema:Boolean"
        }
    ],
    "domainIncludes": [
        {
            "uri": "finance:TradePrice",
            "comment": "A sum of money for which something is or may be bought or sold for trade purposes."
        }
    ]
}