
{
    "label": "groupedTransactionSpecifiedQuantity",
    "uri": "finance:FinancingRequestDocument.groupedTransactionSpecifiedQuantity",
    "comment": "The number of grouped transactions specified in this financing request document.",
    "domain": "finance",
    "rangeIncludes": [
        {
            "uri": "core:QuantityType"
        }
    ],
    "domainIncludes": [
        {
            "uri": "finance:FinancingRequestDocument",
            "comment": "The set of characteristics shared by all individual transactions grouped for this financing request document."
        }
    ]
}