
{
    "label": "streetName",
    "uri": "finance:FinancialInstitutionAddress.streetName",
    "comment": "A name, expressed as text, of a street or thoroughfare for this trade address.",
    "domain": "finance",
    "rangeIncludes": [
        {
            "uri": "schema:Text"
        }
    ],
    "domainIncludes": [
        {
            "uri": "finance:FinancialInstitutionAddress",
            "comment": "The location at which a financial institution may be found or reached."
        }
    ]
}