
{
    "label": "food_production_process_control_product_transportation_procedures",
    "uri": "sustainability:food_production_process_control_product_transportation_procedures",
    "comment": "Does the standard require control processes to be in place for product transportation procedures",
    "rangeIncludes": [
        {
            "uri": "xsd:boolean"
        }
    ],
    "domainIncludes": [
        {
            "uri": "sustainability:ProcessAndProductControl",
            "comment": ""
        }
    ]
}