
{
    "label": "includedNote",
    "uri": "unece:includedNote",
    "comment": [
        "A note included for this document status.",
        "A note included in this document line.",
        "A note included in this exchanged document.",
        "A note included in this referenced document.",
        "A note included in this supply chain trade transaction."
    ],
    "rangeIncludes": [
        {
            "uri": "unece:Note",
            "comment": "A textual or coded description, such as a remark or additional information."
        }
    ],
    "domainIncludes": [
        {
            "uri": "unece:Document",
            "comment": "Written, printed or electronic matter that is referenced."
        },
        {
            "uri": "unece:DocumentLineDocument",
            "comment": "A collection of data for a line on a piece of written, printed or electronic matter that provides information or evidence."
        },
        {
            "uri": "unece:DocumentStatus",
            "comment": "The information relevant to a condition related to a document."
        },
        {
            "uri": "unece:ExchangedDocument",
            "comment": "A collection of data for a piece of written, printed or electronic matter that is exchanged between two or more parties."
        },
        {
            "uri": "unece:SupplyChainTradeTransaction",
            "comment": "A group of supply chain trade line items, trade agreement, trade delivery and trade settlement details."
        }
    ]
}