{
    "label": "InformationSource",
    "uri": "unece:InformationSource",
    "comment": "A person, organization, thing or place from which information comes, arises or is obtained.",
    "businessDomain": "core",
    "datatypeProperties": [
        {
            "uri": "unece:securityInformation",
            "type": "schema:Text",
            "comment": "Security information, expressed as text, of this specified information source."
        }
    ],
    "referencedBy": [
        {
            "uri": "unece:cooperativeInformationSource",
            "comment": "A cooperative information source specified for this trade party."
        },
        {
            "uri": "unece:usedInformationSource",
            "comment": "A specified cooperative information source used for or from this cooperating organization."
        }
    ]
}