
{
    "label": "jobTitle",
    "uri": "unece:jobTitle",
    "comment": "The job title, position or designation, expressed as text, of this trade contact within an organization, such as Director, Software Engineer, Purchasing Manager.",
    "rangeIncludes": [
        {
            "uri": "xsd:string"
        }
    ],
    "domainIncludes": [
        {
            "uri": "unece:Contact",
            "comment": "A person or department that acts as a point of contact with another person or department."
        }
    ]
}