
{
    "label": "other_biodiversity_e_g_offsets_compensation_policies",
    "uri": "sustainability:other_biodiversity_e_g_offsets_compensation_policies",
    "comment": "Other criteria related to biodiversity not covered above.Does the standard include additional criteria related to biodiversity not covered above?",
    "rangeIncludes": [
        {
            "uri": "xsd:boolean"
        }
    ],
    "domainIncludes": [
        {
            "uri": "sustainability:Biodiversity",
            "comment": ""
        }
    ]
}