{
    "label": "Plot",
    "uri": "unece:Plot",
    "comment": "A small piece of land or water used for a crop such as an agricultural or aquacultural crop.",
    "businessDomain": "agriculture",
    "datatypeProperties": [
        {
            "uri": "unece:applicableAgriculturalProcess",
            "type": "unece:AgriculturalProcess",
            "comment": "An agricultural process crop production applicable for this field crop."
        },
        {
            "uri": "unece:appliedAgriculturalApplication",
            "type": "unece:AgriculturalApplication",
            "comment": "Any substance such as seed, fertilizer, water, gas or chemical applied to an agricultural field, substrate, construction, plant, animal or product."
        },
        {
            "uri": "unece:areaMeasure",
            "type": "unece:MeasureType",
            "comment": ""
        },
        {
            "uri": "unece:endDateTime",
            "type": "schema:Text",
            "comment": "The date, time, date time or other date time value for the end of this available period of time."
        },
        {
            "uri": "unece:grownCrop",
            "type": "unece:FieldCrop",
            "comment": "A field crop grown on this crop plot."
        },
        {
            "uri": "unece:regulatoryOrganicIndicator",
            "type": "schema:Boolean",
            "comment": "The indication of whether or not this crop plot is certified as regulatory organic."
        },
        {
            "uri": "unece:regulatorySoilTypeCode",
            "type": "schema:Text",
            "comment": "The code specifying the type of regulatory soil for this crop plot."
        },
        {
            "uri": "unece:specifiedAgriculturalCertificate",
            "type": "unece:AgriculturalCertificate",
            "comment": "A legal proof of ownership, worthiness or qualification to operate an agricultural item."
        },
        {
            "uri": "unece:specifiedAgriculturalCharacteristic",
            "type": "unece:AgriculturalCharacteristic",
            "comment": "A prominent attribute or aspect of an agricultural object."
        },
        {
            "uri": "unece:specifiedArea",
            "type": "unece:Area",
            "comment": "An agricultural zone area specified for this crop plot."
        },
        {
            "uri": "unece:specifiedLocation",
            "type": "unece:Location",
            "comment": "A reference to a physical location or place."
        },
        {
            "uri": "unece:startDateTime",
            "type": "schema:Text",
            "comment": "The date, time, date time or other date time value for the start of this available period of time."
        }
    ],
    "referencedBy": [
        {
            "uri": "unece:grownPlot",
            "comment": "The plot where this field crop is grown."
        },
        {
            "uri": "unece:specifiedPlot",
            "comment": "A crop plot specified for this agricultural application."
        }
    ]
}