
{
    "label": "attachedBinaryFile",
    "uri": "unece:ProcessCertificate.attachedBinaryFile",
    "comment": "A binary file attached for this sustainability inspection.",
    "rangeIncludes": [
        {
            "uri": "unece:BinaryFile",
            "comment": "A specified computer file or program stored in a binary format."
        }
    ],
    "domainIncludes": [
        {
            "uri": "unece:ProcessCertificate",
            "comment": "A piece of written, printed or electronic matter that provides information or evidence that a process has met required criteria."
        }
    ]
}