{
    "label": "repairInformation",
    "uri": "untp-core:repairInformation",
    "comment": [
        "A URI pointing to repair instructions for this product."
    ],
    "rangeIncludes": [
        {
            "uri": "untp-core:Link",
            "comment": "A structure to provide a URL link plus metadata associated with the link."
        }
    ],
    "domainIncludes": [
        {
            "uri": "untp-core:CircularityPerformance",
            "comment": "High level corcularity information about this product.  Note that this doens not substitute for detailed product circularity data sheet (PCDS) criteria which would be represented as a set of conformity claims against individual ISO PCDS criteria."
        }
    ]
}