
{
    "label": "traceability_records_maintained_through_entire_chain_of_production",
    "uri": "sustainability:traceability_records_maintained_through_entire_chain_of_production",
    "comment": "Does the standard require that traceability records are maintained through the entire chain of production for non-food products",
    "rangeIncludes": [
        {
            "uri": "xsd:boolean"
        }
    ],
    "domainIncludes": [
        {
            "uri": "sustainability:TraceabilityAndRecall",
            "comment": ""
        },
        {
            "uri": "sustainability:TracebilityRecallAndAllergens",
            "comment": ""
        }
    ]
}