
{
    "label": "netIncludingTaxesLineTotalAmount",
    "uri": "unece:TradeSettlementLineMonetarySummation.netIncludingTaxesLineTotalAmount",
    "comment": "A monetary value of the total of all line amounts, including line level allowances and charges and including line level taxes, being reported in this trade settlement header monetary summation.",
    "rangeIncludes": [
        {
            "uri": "unece:AmountType",
            "comment": ""
        }
    ],
    "domainIncludes": [
        {
            "uri": "unece:TradeSettlementLineMonetarySummation",
            "comment": "A collection of monetary amount totals, specified at line level, for a trade settlement."
        }
    ]
}