
{
    "label": "remainingRequestedQuantity",
    "uri": "trade:HeaderTradeDelivery.remainingRequestedQuantity",
    "comment": "The remaining quantity, at header level, requested for this trade delivery.",
    "rangeIncludes": [
        {
            "uri": "core:QuantityType"
        }
    ],
    "domainIncludes": [
        {
            "uri": "trade:HeaderTradeDelivery",
            "comment": "Shipping arrangements and movement of products and or services including despatch and delivery at a header level."
        }
    ]
}