
{
    "label": "combinedMachine",
    "uri": "trade:ProductionDevice.combinedMachine",
    "comment": "A production machine combined with this production machine.",
    "domain": "trade",
    "rangeIncludes": [
        {
            "uri": "trade:Machine",
            "comment": "An apparatus specified to be used to perform an activity to produce something."
        }
    ],
    "domainIncludes": [
        {
            "uri": "trade:ProductionDevice",
            "comment": "An object, especially a piece of mechanical or electronic equipment, made or adapted in order to perform a production activity."
        }
    ]
}