
{
    "label": "inputCapacityMeasure",
    "uri": "trade:ProductionDevice.inputCapacityMeasure",
    "comment": "A measure of the input capacity for this production facility.",
    "domain": "trade",
    "rangeIncludes": [
        {
            "uri": "core:MeasureType"
        }
    ],
    "domainIncludes": [
        {
            "uri": "trade:ProductionDevice",
            "comment": "An object, especially a piece of mechanical or electronic equipment, made or adapted in order to perform a production activity."
        }
    ]
}