
{
    "label": "automaticDataCaptureMethodTypeCode",
    "uri": "transport:Marking.automaticDataCaptureMethodTypeCode",
    "comment": "A code specifying an automatic data capture method type for this packaging marking.",
    "domain": "transport",
    "rangeIncludes": [
        {
            "uri": "transport:AutomaticDataCaptureMethodCodeList"
        }
    ],
    "domainIncludes": [
        {
            "uri": "transport:Marking",
            "comment": "An inscription, stamp or label on packaging, such as to indicate date, ownership, quality, manufacture or origin."
        }
    ]
}