{
    "label": "transportEquipmentSplitGoodsIndicator",
    "uri": "unece:transportEquipmentSplitGoodsIndicator",
    "comment": "The indication of whether or not the goods in this supply chain consignment are split across more than one piece of transport equipment.",
    "rangeIncludes": [
        {
            "uri": "xsd:boolean"
        }
    ],
    "domainIncludes": [
        {
            "uri": "unece:Consignment",
            "comment": "A separately identifiable collection of ..."
        }
    ]
}