
{
    "label": "TTAggregationEvent",
    "uri": "unece:TTAggregationEvent",
    "comment": "A Track and Trace (TT) event where objects or processes are grouped.",
    "objectProperties": [
        {
            "uri": "unece:actionCode",
            "type": "xsd:string",
            "comment": "The code specifying the action for this TT aggregation event."
        },
        {
            "uri": "unece:businessStepCode",
            "type": "xsd:string",
            "comment": "The code specifying the business step for this TT aggregation event."
        },
        {
            "uri": "unece:childObjectInstanceId",
            "type": "xsd:string",
            "comment": "An instance identifier for a child object of this TT aggregation event."
        },
        {
            "uri": "unece:childQuantitySpecifiedEventElement",
            "type": "unece:EventElement",
            "comment": "A quantity event element specified for a child of this TT aggregation event."
        },
        {
            "uri": "unece:destinationRelatedParty",
            "type": "unece:TTParty",
            "comment": "A destination related party for this TT aggregation event."
        },
        {
            "uri": "unece:dispositionCode",
            "type": "xsd:string",
            "comment": "The code specifying the disposition related to this TT aggregation event."
        },
        {
            "uri": "unece:identifier",
            "type": "xsd:string",
            "comment": "The identifier for this TT aggregation event."
        },
        {
            "uri": "unece:occurrenceDateTime",
            "type": "xsd:string",
            "comment": "The date, time, date time, or other date time value at which this TT aggregation event occurred."
        },
        {
            "uri": "unece:parentObjectId",
            "type": "xsd:string",
            "comment": "The identifier of the parent object for this TT aggregation event."
        },
        {
            "uri": "unece:readPointRelatedLocation",
            "type": "unece:TTLocation",
            "comment": "The read point related location of this TT aggregation event."
        },
        {
            "uri": "unece:recordedDateTime",
            "type": "xsd:string",
            "comment": "The date, time, date time, or other date time value at which this TT aggregation event was recorded."
        },
        {
            "uri": "unece:relatedCertification",
            "type": "unece:SpecifiedCertification",
            "comment": "A certification related to this TT aggregation event."
        },
        {
            "uri": "unece:relatedTTLocation",
            "type": "unece:TTLocation",
            "comment": "The location related to this TT aggregation event."
        },
        {
            "uri": "unece:sourceRelatedParty",
            "type": "unece:TTParty",
            "comment": "A source related party for this TT aggregation event."
        },
        {
            "uri": "unece:specifiedError",
            "type": "unece:Error",
            "comment": "A declared error specified for this TT aggregation event."
        },
        {
            "uri": "unece:specifiedTradeTransaction",
            "type": "unece:TTTradeTransaction",
            "comment": "A trade transaction specified for this TT aggregation event."
        }
    ]
}