
{
    "label": "UniversalCommunication",
    "uri": "unece:UniversalCommunication",
    "comment": "The exchange of thoughts, messages, or information, as universally exchanged by speech, signals, writing, or behaviour between persons and/or organizations.",
    "datatypeProperties": [
        {
            "uri": "unece:communicationChannelCode",
            "type": "unece:UNCL3155Code",
            "comment": "The code specifying the channel or manner in which a universal communication can be made, such as telephone or email."
        },
        {
            "uri": "unece:completeNumber",
            "type": "xsd:string",
            "comment": "The text string of characters that make up the complete number for this universal communication."
        },
        {
            "uri": "unece:uRIId",
            "type": "xsd:token",
            "comment": "The Uniform Resource Identifier (URI), such as a web or an email address, for this universal communication."
        }
    ],
    "referencedBy": [
        {
            "uri": "unece:directTelephoneCommunication",
            "comment": "The direct telephone communication information for this trade contact."
        },
        {
            "uri": "unece:emailURICommunication",
            "comment": "The email URI (Uniform Resource ..."
        },
        {
            "uri": "unece:endPointURICommunication",
            "comment": "The communication address of the end point URI for this trade party."
        },
        {
            "uri": "unece:faxCommunication",
            "comment": "Fax communication information for this ..."
        },
        {
            "uri": "unece:instantMessagingCommunication",
            "comment": "Instant messaging communication information for this trade contact."
        },
        {
            "uri": "unece:landlineTelephoneCommunication",
            "comment": "Landline telephone communication information for this transport person."
        },
        {
            "uri": "unece:mobileTelephoneCommunication",
            "comment": "Mobile telephone communication information for ..."
        },
        {
            "uri": "unece:telephoneCommunication",
            "comment": "A telephone communication for this ..."
        },
        {
            "uri": "unece:telexCommunication",
            "comment": "Telegraphy (Telex) communication information for this trade contact."
        },
        {
            "uri": "unece:uRICommunication",
            "comment": "A Uniform Resource Identifier (URI) ..."
        },
        {
            "uri": "unece:vOIPCommunication",
            "comment": "Voice Over Internet Protocol (VOIP) communication information for this trade contact."
        }
    ]
}